cosmoGW/GW_analytical.py
cosmoGW/GW_back.py
cosmoGW/GW_models.py
cosmoGW/GW_templates.py
cosmoGW/__init__.py
cosmoGW/analysis.py
cosmoGW/cosmology.py
cosmoGW/hydro_bubbles.py
cosmoGW/interferometry.py
cosmoGW/plot_sets.py
cosmoGW/utils.py
cosmoGW/resources/__init__.py
cosmoGW/resources/__pycache__/__init__.cpython-313.pyc
cosmoGW/resources/cosmoGW.egg-info/PKG-INFO
cosmoGW/resources/cosmoGW.egg-info/SOURCES.txt
cosmoGW/resources/cosmoGW.egg-info/dependency_links.txt
cosmoGW/resources/cosmoGW.egg-info/requires.txt
cosmoGW/resources/cosmoGW.egg-info/top_level.txt
cosmoGW/resources/cosmology/T_gs.csv
cosmoGW/resources/cosmology/__init__.py
cosmoGW/resources/cosmology/__pycache__/__init__.cpython-313.pyc
cosmoGW/resources/detectors_sensitivity/AEDGE.csv
cosmoGW/resources/detectors_sensitivity/AION.csv
cosmoGW/resources/detectors_sensitivity/DECIGO_PLS_SNR10.csv
cosmoGW/resources/detectors_sensitivity/Gaia_PLS_SNR10.csv
cosmoGW/resources/detectors_sensitivity/LISA_Omega.csv
cosmoGW/resources/detectors_sensitivity/LISA_OmegaPLS.csv
cosmoGW/resources/detectors_sensitivity/LISA_Taiji_Xi.csv
cosmoGW/resources/detectors_sensitivity/LISA_Taiji_Xi_PLS.csv
cosmoGW/resources/detectors_sensitivity/LISA_Xi.csv
cosmoGW/resources/detectors_sensitivity/LISA_Xi_PLS.csv
cosmoGW/resources/detectors_sensitivity/LISA_response_f.csv
cosmoGW/resources/detectors_sensitivity/LISA_response_f_TDI.csv
cosmoGW/resources/detectors_sensitivity/LISA_response_f_X.csv
cosmoGW/resources/detectors_sensitivity/OmegaPLS_Caprinietal19.csv
cosmoGW/resources/detectors_sensitivity/README.md
cosmoGW/resources/detectors_sensitivity/SKA_PLS_SNR10.csv
cosmoGW/resources/detectors_sensitivity/Taiji_Omega.csv
cosmoGW/resources/detectors_sensitivity/Taiji_Omega_PLS.csv
cosmoGW/resources/detectors_sensitivity/Taiji_Xi.csv
cosmoGW/resources/detectors_sensitivity/Taiji_Xi_PLS.csv
cosmoGW/resources/detectors_sensitivity/Taiji_response_f.csv
cosmoGW/resources/detectors_sensitivity/Taiji_response_f_TDI.csv
cosmoGW/resources/detectors_sensitivity/Taiji_response_f_X.csv
cosmoGW/resources/detectors_sensitivity/Theia_PLS_SNR10.csv
cosmoGW/resources/detectors_sensitivity/XiPLS_Ellisetal19.csv
cosmoGW/resources/detectors_sensitivity/binaries_LLR_2038.csv
cosmogw-0.0.39.dist-info/licenses/LICENSE
cosmogw-0.0.39.dist-info/METADATA
cosmogw-0.0.39.dist-info/WHEEL
cosmogw-0.0.39.dist-info/top_level.txt
cosmogw-0.0.39.dist-info/RECORD
