Metadata-Version: 2.4
Name: cosmoGW
Version: 0.0.39
Summary: code for cosmological gravitational wave backgrounds
Author-email: Alberto Roper Pol <alberto.roperpol@unige.ch>
Project-URL: Homepage, https://github.com/cosmoGW/cosmoGW
Classifier: Programming Language :: Python :: 3
Classifier: Operating System :: OS Independent
Classifier: License :: OSI Approved :: GNU General Public License v3 (GPLv3)
Requires-Python: >=3.8
License-File: LICENSE
Requires-Dist: matplotlib
Requires-Dist: numpy
Requires-Dist: pandas
Requires-Dist: astropy
Requires-Dist: scipy
Dynamic: license-file
